q_exporter/__init__.py
q_exporter/main.py
q_exporter-0.1.0.dist-info/METADATA
q_exporter-0.1.0.dist-info/WHEEL
q_exporter-0.1.0.dist-info/licenses/LICENSE
q_exporter-0.1.0.dist-info/RECORD
