Metadata-Version: 2.4
Name: q_exporter
Version: 0.1.0
Summary: Q+/KDB Exporter
Project-URL: Homepage, https://github.com/johnbenedictyan/q_exporter
Project-URL: Issues, https://github.com/johnbenedictyan/q_exporter/issues
Author-email: John Benedict Yan <johnbenedictyan+q_exporter@gmail.com>
License-Expression: MIT
License-File: LICENSE
Classifier: Operating System :: OS Independent
Classifier: Programming Language :: Python :: 3
Requires-Python: >=3.13
